[
  {
    "word": "lisanin",
    "translation": "abandon"
  },
  {
    "word": "kakayahan",
    "translation": "ability"
  },
  {
    "word": "kaya",
    "translation": "able"
  },
  {
    "word": "pagpapalaglag",
    "translation": "abortion"
  },
  {
    "word": "tungkol sa",
    "translation": "about"
  },
  {
    "word": "sa itaas",
    "translation": "above"
  },
  {
    "word": "ibang bansa",
    "translation": "abroad"
  },
  {
    "word": "kawalan",
    "translation": "absence"
  },
  {
    "word": "tiyak",
    "translation": "absolute"
  },
  {
    "word": "walang pasubali",
    "translation": "absolutely"
  },
  {
    "word": "humithit",
    "translation": "absorb"
  },
  {
    "word": "abuso",
    "translation": "abuse"
  },
  {
    "word": "akademiko",
    "translation": "academic"
  },
  {
    "word": "tanggapin",
    "translation": "accept"
  },
  {
    "word": "makagamit",
    "translation": "access"
  },
  {
    "word": "aksidente",
    "translation": "accident"
  },
  {
    "word": "samahan",
    "translation": "accompany"
  },
  {
    "word": "tuparin",
    "translation": "accomplish"
  },
  {
    "word": "alinsunod",
    "translation": "according"
  },
  {
    "word": "kuwenta",
    "translation": "account"
  },
  {
    "word": "wasto",
    "translation": "accurate"
  },
  {
    "word": "akusahan",
    "translation": "accuse"
  },
  {
    "word": "makamit",
    "translation": "achieve"
  },
  {
    "word": "nakamtan",
    "translation": "achievement"
  },
  {
    "word": "asido",
    "translation": "acid"
  },
  {
    "word": "kinikilala",
    "translation": "acknowledge"
  },
  {
    "word": "makuha",
    "translation": "acquire"
  },
  {
    "word": "sa kabila",
    "translation": "across"
  },
  {
    "word": "kumilos",
    "translation": "act"
  },
  {
    "word": "gawa",
    "translation": "action"
  },
  {
    "word": "aktibo",
    "translation": "active"
  },
  {
    "word": "masugid na tao",
    "translation": "activist"
  },
  {
    "word": "gawain",
    "translation": "activity"
  },
  {
    "word": "lalaking aktor",
    "translation": "actor"
  },
  {
    "word": "babaeng aktor",
    "translation": "actress"
  },
  {
    "word": "kasalukuyan",
    "translation": "actual"
  },
  {
    "word": "katunayan",
    "translation": "actually"
  },
  {
    "word": "iangkop",
    "translation": "adapt"
  },
  {
    "word": "magdagdag",
    "translation": "add"
  },
  {
    "word": "dugtong",
    "translation": "addition"
  },
  {
    "word": "karagdagan",
    "translation": "additional"
  },
  {
    "word": "talumpati",
    "translation": "address"
  },
  {
    "word": "sapat",
    "translation": "adequate"
  },
  {
    "word": "isaayos",
    "translation": "adjust"
  },
  {
    "word": "pag-aayos",
    "translation": "adjustment"
  },
  {
    "word": "pangangasiwa",
    "translation": "administration"
  },
  {
    "word": "tagapangasiwa",
    "translation": "administrator"
  },
  {
    "word": "hangaan",
    "translation": "admire"
  },
  {
    "word": "pagtanggap",
    "translation": "admission"
  },
  {
    "word": "umamin",
    "translation": "admit"
  },
  {
    "word": "nagbibinata o nagdadalaga",
    "translation": "adolescent"
  },
  {
    "word": "ampunin",
    "translation": "adopt"
  },
  {
    "word": "matanda",
    "translation": "adult"
  },
  {
    "word": "sulong",
    "translation": "advance"
  },
  {
    "word": "kalamangan",
    "translation": "advantage"
  },
  {
    "word": "pakikipagsapalaran",
    "translation": "adventure"
  },
  {
    "word": "pag-aanunsiyo",
    "translation": "advertising"
  },
  {
    "word": "payo",
    "translation": "advice"
  },
  {
    "word": "paalalahan",
    "translation": "advise"
  },
  {
    "word": "tagapayo",
    "translation": "adviser"
  },
  {
    "word": "tagataguyod",
    "translation": "advocate"
  },
  {
    "word": "kapakanan",
    "translation": "affair"
  },
  {
    "word": "dulot",
    "translation": "affect"
  },
  {
    "word": "makaya",
    "translation": "afford"
  },
  {
    "word": "takot",
    "translation": "afraid"
  },
  {
    "word": "pagkatapos",
    "translation": "after"
  },
  {
    "word": "hapon",
    "translation": "afternoon"
  },
  {
    "word": "muli",
    "translation": "again"
  },
  {
    "word": "salungat",
    "translation": "against"
  },
  {
    "word": "edad",
    "translation": "age"
  },
  {
    "word": "tanggapan",
    "translation": "agency"
  },
  {
    "word": "balakin",
    "translation": "agenda"
  },
  {
    "word": "ahente",
    "translation": "agent"
  },
  {
    "word": "agresibo",
    "translation": "aggressive"
  },
  {
    "word": "nakararaan",
    "translation": "ago"
  },
  {
    "word": "sumang-ayon",
    "translation": "agree"
  },
  {
    "word": "kasunduan",
    "translation": "agreement"
  },
  {
    "word": "agrikultura",
    "translation": "agricultural"
  },
  {
    "word": "nauuna",
    "translation": "ahead"
  },
  {
    "word": "tulong",
    "translation": "aid"
  },
  {
    "word": "pantulong",
    "translation": "aide"
  },
  {
    "word": "pakay",
    "translation": "aim"
  },
  {
    "word": "himpapawid",
    "translation": "air"
  },
  {
    "word": "mga sasakyang panghimpapawid",
    "translation": "aircraft"
  },
  {
    "word": "kompanya ng eroplano",
    "translation": "airline"
  },
  {
    "word": "paliparan",
    "translation": "airport"
  },
  {
    "word": "alkohol",
    "translation": "alcohol"
  },
  {
    "word": "buhay",
    "translation": "alive"
  },
  {
    "word": "lahat",
    "translation": "all"
  },
  {
    "word": "alyansa",
    "translation": "alliance"
  },
  {
    "word": "payagan",
    "translation": "allow"
  },
  {
    "word": "kapanig",
    "translation": "ally"
  },
  {
    "word": "kapanig",
    "translation": "ally"
  },
  {
    "word": "halos",
    "translation": "almost"
  },
  {
    "word": "nag-iisa",
    "translation": "alone"
  },
  {
    "word": "sa tabi",
    "translation": "along"
  },
  {
    "word": "na",
    "translation": "already"
  },
  {
    "word": "din",
    "translation": "also"
  },
  {
    "word": "alter",
    "translation": "alter"
  },
  {
    "word": "alternatibo",
    "translation": "alternative"
  },
  {
    "word": "bagaman",
    "translation": "although"
  },
  {
    "word": "palagi",
    "translation": "always"
  },
  {
    "word": "AM",
    "translation": "AM"
  },
  {
    "word": "kagulat-gulat",
    "translation": "amazing"
  },
  {
    "word": "Amerikano",
    "translation": "American"
  },
  {
    "word": "sa gitna ng",
    "translation": "among"
  },
  {
    "word": "dami",
    "translation": "amount"
  },
  {
    "word": "pagsusuri",
    "translation": "analysis"
  },
  {
    "word": "analyst",
    "translation": "analyst"
  },
  {
    "word": "suriin",
    "translation": "analyze"
  },
  {
    "word": "sinauna",
    "translation": "ancient"
  },
  {
    "word": "at",
    "translation": "and"
  },
  {
    "word": "galit",
    "translation": "anger"
  },
  {
    "word": "anggulo",
    "translation": "angle"
  },
  {
    "word": "galit",
    "translation": "angry"
  },
  {
    "word": "hayop",
    "translation": "animal"
  },
  {
    "word": "anibersaryo",
    "translation": "anniversary"
  },
  {
    "word": "ipahayag",
    "translation": "announce"
  },
  {
    "word": "taunan",
    "translation": "annual"
  },
  {
    "word": "isa pa",
    "translation": "another"
  },
  {
    "word": "sagot",
    "translation": "answer"
  },
  {
    "word": "umasa",
    "translation": "anticipate"
  },
  {
    "word": "pagkabahala",
    "translation": "anxiety"
  },
  {
    "word": "anuman",
    "translation": "any"
  },
  {
    "word": "sinuman",
    "translation": "anybody"
  },
  {
    "word": "anymore",
    "translation": "anymore"
  },
  {
    "word": "sinuman",
    "translation": "anyone"
  },
  {
    "word": "anumang bagay",
    "translation": "anything"
  },
  {
    "word": "gayon pa man",
    "translation": "anyway"
  },
  {
    "word": "kahit saan",
    "translation": "anywhere"
  },
  {
    "word": "bukod",
    "translation": "apart"
  },
  {
    "word": "apartment",
    "translation": "apartment"
  },
  {
    "word": "malinaw",
    "translation": "apparent"
  },
  {
    "word": "tila",
    "translation": "apparently"
  },
  {
    "word": "panawagan",
    "translation": "appeal"
  },
  {
    "word": "lumitaw",
    "translation": "appear"
  },
  {
    "word": "anyo",
    "translation": "appearance"
  },
  {
    "word": "mansanas",
    "translation": "apple"
  },
  {
    "word": "aplikasyon",
    "translation": "application"
  },
  {
    "word": "gamitin",
    "translation": "apply"
  },
  {
    "word": "humirang",
    "translation": "appoint"
  },
  {
    "word": "appointment",
    "translation": "appointment"
  },
  {
    "word": "pahalagahan",
    "translation": "appreciate"
  },
  {
    "word": "lapitan",
    "translation": "approach"
  },
  {
    "word": "angkop",
    "translation": "appropriate"
  },
  {
    "word": "pagsang-ayon",
    "translation": "approval"
  },
  {
    "word": "pagpayag",
    "translation": "approve"
  },
  {
    "word": "halos",
    "translation": "approximately"
  },
  {
    "word": "Arab",
    "translation": "Arab"
  },
  {
    "word": "arkitekto",
    "translation": "architect"
  },
  {
    "word": "lugar",
    "translation": "area"
  },
  {
    "word": "magtalo",
    "translation": "argue"
  },
  {
    "word": "pagtatalo",
    "translation": "argument"
  },
  {
    "word": "tumindig",
    "translation": "arise"
  },
  {
    "word": "braso",
    "translation": "arm"
  },
  {
    "word": "armado",
    "translation": "armed"
  },
  {
    "word": "hukbo",
    "translation": "army"
  },
  {
    "word": "sa paligid",
    "translation": "around"
  },
  {
    "word": "mag-ayos",
    "translation": "arrange"
  },
  {
    "word": "pagsasaayos",
    "translation": "arrangement"
  },
  {
    "word": "arestuhin",
    "translation": "arrest"
  },
  {
    "word": "pagdating",
    "translation": "arrival"
  },
  {
    "word": "dumating",
    "translation": "arrive"
  },
  {
    "word": "sining",
    "translation": "art"
  },
  {
    "word": "artikulo",
    "translation": "article"
  },
  {
    "word": "pintor",
    "translation": "artist"
  },
  {
    "word": "masining",
    "translation": "artistic"
  },
  {
    "word": "gaya ng",
    "translation": "as"
  },
  {
    "word": "Asyano",
    "translation": "Asian"
  },
  {
    "word": "bukod",
    "translation": "aside"
  },
  {
    "word": "itanong",
    "translation": "ask"
  },
  {
    "word": "natutulog",
    "translation": "asleep"
  },
  {
    "word": "aspeto",
    "translation": "aspect"
  },
  {
    "word": "pag-atake",
    "translation": "assault"
  },
  {
    "word": "igiit",
    "translation": "assert"
  },
  {
    "word": "masuri",
    "translation": "assess"
  },
  {
    "word": "pagtatasa",
    "translation": "assessment"
  },
  {
    "word": "pag-aari",
    "translation": "asset"
  },
  {
    "word": "magtalaga",
    "translation": "assign"
  },
  {
    "word": "takdang-aralin",
    "translation": "assignment"
  },
  {
    "word": "tumulong",
    "translation": "assist"
  },
  {
    "word": "tulong",
    "translation": "assistance"
  },
  {
    "word": "katulong",
    "translation": "assistant"
  },
  {
    "word": "makisama",
    "translation": "associate"
  },
  {
    "word": "samahan",
    "translation": "association"
  },
  {
    "word": "ipalagay",
    "translation": "assume"
  },
  {
    "word": "palagay",
    "translation": "assumption"
  },
  {
    "word": "tiyakin, siguruhin",
    "translation": "assure"
  },
  {
    "word": "sa",
    "translation": "at"
  },
  {
    "word": "atleta",
    "translation": "athlete"
  },
  {
    "word": "malakas",
    "translation": "athletic"
  },
  {
    "word": "atmospera",
    "translation": "atmosphere"
  },
  {
    "word": "atake",
    "translation": "attack"
  },
  {
    "word": "tangka",
    "translation": "attempt"
  },
  {
    "word": "dalo",
    "translation": "attend"
  },
  {
    "word": "pansin",
    "translation": "attention"
  },
  {
    "word": "ugali",
    "translation": "attitude"
  },
  {
    "word": "abogado",
    "translation": "attorney"
  },
  {
    "word": "akit",
    "translation": "attract"
  },
  {
    "word": "kaakit-akit",
    "translation": "attractive"
  },
  {
    "word": "katangian",
    "translation": "attribute"
  },
  {
    "word": "madla",
    "translation": "audience"
  },
  {
    "word": "may akda",
    "translation": "author"
  },
  {
    "word": "awtoridad",
    "translation": "authority"
  },
  {
    "word": "awtomatiko",
    "translation": "auto"
  },
  {
    "word": "magagamit",
    "translation": "available"
  },
  {
    "word": "pangkaraniwan",
    "translation": "average"
  },
  {
    "word": "iwas",
    "translation": "avoid"
  },
  {
    "word": "parangal",
    "translation": "award"
  },
  {
    "word": "may kamalayan",
    "translation": "aware"
  },
  {
    "word": "kamalayan",
    "translation": "awareness"
  },
  {
    "word": "malayo",
    "translation": "away"
  },
  {
    "word": "kakila-kilabot",
    "translation": "awful"
  },
  {
    "word": "sanggol",
    "translation": "baby"
  },
  {
    "word": "likod",
    "translation": "back"
  },
  {
    "word": "background",
    "translation": "background"
  },
  {
    "word": "masama",
    "translation": "bad"
  },
  {
    "word": "kinasasama",
    "translation": "badly"
  },
  {
    "word": "bag",
    "translation": "bag"
  },
  {
    "word": "maghurno",
    "translation": "bake"
  },
  {
    "word": "balanse",
    "translation": "balance"
  },
  {
    "word": "bola",
    "translation": "ball"
  },
  {
    "word": "pagbabawal",
    "translation": "ban"
  },
  {
    "word": "banda",
    "translation": "band"
  },
  {
    "word": "bangko",
    "translation": "bank"
  },
  {
    "word": "inuman",
    "translation": "bar"
  },
  {
    "word": "bahagya",
    "translation": "barely"
  },
  {
    "word": "bariles",
    "translation": "barrel"
  },
  {
    "word": "harang",
    "translation": "barrier"
  },
  {
    "word": "base",
    "translation": "base"
  },
  {
    "word": "pangunahing",
    "translation": "basic"
  },
  {
    "word": "talaga",
    "translation": "basically"
  },
  {
    "word": "batayan",
    "translation": "basis"
  },
  {
    "word": "buslo",
    "translation": "basket"
  },
  {
    "word": "basketbol",
    "translation": "basketball"
  },
  {
    "word": "banyo",
    "translation": "bathroom"
  },
  {
    "word": "baterya",
    "translation": "battery"
  },
  {
    "word": "labanan",
    "translation": "battle"
  },
  {
    "word": "maging",
    "translation": "be"
  },
  {
    "word": "dalampasigan",
    "translation": "beach"
  },
  {
    "word": "buto",
    "translation": "bean"
  },
  {
    "word": "oso",
    "translation": "bear"
  },
  {
    "word": "talunin",
    "translation": "beat"
  },
  {
    "word": "maganda",
    "translation": "beautiful"
  },
  {
    "word": "kagandahan",
    "translation": "beauty"
  },
  {
    "word": "dahil",
    "translation": "because"
  },
  {
    "word": "maging",
    "translation": "become"
  },
  {
    "word": "kama",
    "translation": "bed"
  },
  {
    "word": "silid-tulugan",
    "translation": "bedroom"
  },
  {
    "word": "serbesa",
    "translation": "beer"
  },
  {
    "word": "bago",
    "translation": "before"
  },
  {
    "word": "magsimula",
    "translation": "begin"
  },
  {
    "word": "simula",
    "translation": "beginning"
  },
  {
    "word": "pag-uugali",
    "translation": "behavior"
  },
  {
    "word": "sa likuran",
    "translation": "behind"
  },
  {
    "word": "pagiging",
    "translation": "being"
  },
  {
    "word": "paniniwala",
    "translation": "belief"
  },
  {
    "word": "maniwala",
    "translation": "believe"
  },
  {
    "word": "kampana",
    "translation": "bell"
  },
  {
    "word": "nabibilang",
    "translation": "belong"
  },
  {
    "word": "sa ibaba",
    "translation": "below"
  },
  {
    "word": "sinturon",
    "translation": "belt"
  },
  {
    "word": "bangko",
    "translation": "bench"
  },
  {
    "word": "yuko",
    "translation": "bend"
  },
  {
    "word": "sa ilalim",
    "translation": "beneath"
  },
  {
    "word": "benepisyo",
    "translation": "benefit"
  },
  {
    "word": "sa tabi",
    "translation": "beside"
  },
  {
    "word": "Bukod sa",
    "translation": "besides"
  },
  {
    "word": "pinakamahusay",
    "translation": "best"
  },
  {
    "word": "pusta",
    "translation": "bet"
  },
  {
    "word": "mas mabuti",
    "translation": "better"
  },
  {
    "word": "sa pagitan",
    "translation": "between"
  },
  {
    "word": "lampas",
    "translation": "beyond"
  },
  {
    "word": "Bibliya",
    "translation": "Bible"
  },
  {
    "word": "malaki",
    "translation": "big"
  },
  {
    "word": "bisikleta",
    "translation": "bike"
  },
  {
    "word": "bayarin",
    "translation": "bill"
  },
  {
    "word": "bilyon",
    "translation": "billion"
  },
  {
    "word": "magbigkis",
    "translation": "bind"
  },
  {
    "word": "Biyolohikal",
    "translation": "biological"
  },
  {
    "word": "ibon",
    "translation": "bird"
  },
  {
    "word": "kapanganakan",
    "translation": "birth"
  },
  {
    "word": "kaarawan",
    "translation": "birthday"
  },
  {
    "word": "kaunti",
    "translation": "bit"
  },
  {
    "word": "kagat",
    "translation": "bite"
  },
  {
    "word": "itim",
    "translation": "black"
  },
  {
    "word": "talim",
    "translation": "blade"
  },
  {
    "word": "sisihin",
    "translation": "blame"
  },
  {
    "word": "kumot",
    "translation": "blanket"
  },
  {
    "word": "bulag",
    "translation": "blind"
  },
  {
    "word": "harangan",
    "translation": "block"
  },
  {
    "word": "huli",
    "translation": "catch"
  },
  {
    "word": "kategorya",
    "translation": "category"
  },
  {
    "word": "Katoliko",
    "translation": "Catholic"
  },
  {
    "word": "dahilan",
    "translation": "cause"
  },
  {
    "word": "kisame",
    "translation": "ceiling"
  },
  {
    "word": "ipagdiwang",
    "translation": "celebrate"
  },
  {
    "word": "pagdiriwang",
    "translation": "celebration"
  },
  {
    "word": "artista",
    "translation": "celebrity"
  },
  {
    "word": "selda",
    "translation": "cell"
  },
  {
    "word": "gitna",
    "translation": "center"
  },
  {
    "word": "sentral",
    "translation": "central"
  },
  {
    "word": "siglo",
    "translation": "century"
  },
  {
    "word": "CEO",
    "translation": "CEO"
  },
  {
    "word": "seremonya",
    "translation": "ceremony"
  },
  {
    "word": "tiyak",
    "translation": "certain"
  },
  {
    "word": "tiyak",
    "translation": "certainly"
  },
  {
    "word": "kadena",
    "translation": "chain"
  },
  {
    "word": "upuan",
    "translation": "chair"
  },
  {
    "word": "tagapangulo",
    "translation": "chairman"
  },
  {
    "word": "hamon",
    "translation": "challenge"
  },
  {
    "word": "kamara",
    "translation": "chamber"
  },
  {
    "word": "kampeon",
    "translation": "champion"
  },
  {
    "word": "kampeonato",
    "translation": "championship"
  },
  {
    "word": "pagkakataon",
    "translation": "chance"
  },
  {
    "word": "pagbabago",
    "translation": "change"
  },
  {
    "word": "nagbabago",
    "translation": "changing"
  },
  {
    "word": "channel",
    "translation": "channel"
  },
  {
    "word": "kabanata",
    "translation": "chapter"
  },
  {
    "word": "pagkatao",
    "translation": "character"
  },
  {
    "word": "katangian",
    "translation": "characteristic"
  },
  {
    "word": "magpakilala",
    "translation": "characterize"
  },
  {
    "word": "bayad",
    "translation": "charge"
  },
  {
    "word": "kawanggawa",
    "translation": "charity"
  },
  {
    "word": "tsart",
    "translation": "chart"
  },
  {
    "word": "habulin",
    "translation": "chase"
  },
  {
    "word": "mura",
    "translation": "cheap"
  },
  {
    "word": "tignan",
    "translation": "check"
  },
  {
    "word": "pisngi",
    "translation": "cheek"
  },
  {
    "word": "keso",
    "translation": "cheese"
  },
  {
    "word": "tagaluto",
    "translation": "chef"
  },
  {
    "word": "kemikal",
    "translation": "chemical"
  },
  {
    "word": "dibdib",
    "translation": "chest"
  },
  {
    "word": "manok",
    "translation": "chicken"
  },
  {
    "word": "hepe",
    "translation": "chief"
  },
  {
    "word": "bata",
    "translation": "child"
  },
  {
    "word": "pagkabata",
    "translation": "childhood"
  },
  {
    "word": "Tsino",
    "translation": "Chinese"
  },
  {
    "word": "pingas",
    "translation": "chip"
  },
  {
    "word": "tsokolate",
    "translation": "chocolate"
  },
  {
    "word": "pagpili",
    "translation": "choice"
  },
  {
    "word": "kolesterol",
    "translation": "cholesterol"
  },
  {
    "word": "pumili",
    "translation": "choose"
  },
  {
    "word": "Kristyano",
    "translation": "Christian"
  },
  {
    "word": "Pasko",
    "translation": "Christmas"
  },
  {
    "word": "simbahan",
    "translation": "church"
  },
  {
    "word": "sigarilyo",
    "translation": "cigarette"
  },
  {
    "word": "bilog",
    "translation": "circle"
  },
  {
    "word": "pangyayari",
    "translation": "circumstance"
  },
  {
    "word": "banggitin",
    "translation": "cite"
  },
  {
    "word": "mamamayan",
    "translation": "citizen"
  },
  {
    "word": "lungsod",
    "translation": "city"
  },
  {
    "word": "sibil",
    "translation": "civil"
  },
  {
    "word": "sibilyan",
    "translation": "civilian"
  },
  {
    "word": "paghahabol",
    "translation": "claim"
  },
  {
    "word": "klase",
    "translation": "class"
  },
  {
    "word": "klasiko",
    "translation": "classic"
  },
  {
    "word": "silid-aralan",
    "translation": "classroom"
  },
  {
    "word": "malinis",
    "translation": "clean"
  },
  {
    "word": "malinaw",
    "translation": "clear"
  },
  {
    "word": "malinaw",
    "translation": "clearly"
  },
  {
    "word": "kliente",
    "translation": "client"
  },
  {
    "word": "klima",
    "translation": "climate"
  },
  {
    "word": "umakyat",
    "translation": "climb"
  },
  {
    "word": "klinika",
    "translation": "clinic"
  },
  {
    "word": "klinikal",
    "translation": "clinical"
  },
  {
    "word": "orasan",
    "translation": "clock"
  },
  {
    "word": "malapit",
    "translation": "close"
  },
  {
    "word": "malapit",
    "translation": "closely"
  },
  {
    "word": "mas malapit",
    "translation": "closer"
  },
  {
    "word": "mga damit",
    "translation": "clothes"
  },
  {
    "word": "damit",
    "translation": "clothing"
  },
  {
    "word": "ulap",
    "translation": "cloud"
  },
  {
    "word": "samahan",
    "translation": "club"
  },
  {
    "word": "pahiwatig",
    "translation": "clue"
  },
  {
    "word": "kumpol",
    "translation": "cluster"
  },
  {
    "word": "tagapagsanay",
    "translation": "coach"
  },
  {
    "word": "uling",
    "translation": "coal"
  },
  {
    "word": "koalisyon",
    "translation": "coalition"
  },
  {
    "word": "baybayin",
    "translation": "coast"
  },
  {
    "word": "pahid",
    "translation": "coat"
  },
  {
    "word": "kodigo",
    "translation": "code"
  },
  {
    "word": "kape",
    "translation": "coffee"
  },
  {
    "word": "nagbibigay-malay",
    "translation": "cognitive"
  },
  {
    "word": "malamig",
    "translation": "cold"
  },
  {
    "word": "pagbagsak",
    "translation": "collapse"
  },
  {
    "word": "kasamahan",
    "translation": "colleague"
  },
  {
    "word": "kolektahin",
    "translation": "collect"
  },
  {
    "word": "koleksyon",
    "translation": "collection"
  },
  {
    "word": "sama-sama",
    "translation": "collective"
  },
  {
    "word": "kolehiyo",
    "translation": "college"
  },
  {
    "word": "dugo",
    "translation": "blood"
  },
  {
    "word": "bughaw",
    "translation": "blue"
  },
  {
    "word": "bangka",
    "translation": "boat"
  },
  {
    "word": "katawan",
    "translation": "body"
  },
  {
    "word": "bomba",
    "translation": "bomb"
  },
  {
    "word": "pambobomba",
    "translation": "bombing"
  },
  {
    "word": "buto",
    "translation": "bone"
  },
  {
    "word": "aklat",
    "translation": "book"
  },
  {
    "word": "bota",
    "translation": "boot"
  },
  {
    "word": "hangganan",
    "translation": "border"
  },
  {
    "word": "ipinanganak",
    "translation": "born"
  },
  {
    "word": "hiramin",
    "translation": "borrow"
  },
  {
    "word": "amo",
    "translation": "boss"
  },
  {
    "word": "kapwa",
    "translation": "both"
  },
  {
    "word": "abala",
    "translation": "bother"
  },
  {
    "word": "bote",
    "translation": "bottle"
  },
  {
    "word": "ilalim",
    "translation": "bottom"
  },
  {
    "word": "hangganan",
    "translation": "boundary"
  },
  {
    "word": "mangkok",
    "translation": "bowl"
  },
  {
    "word": "kahon",
    "translation": "box"
  },
  {
    "word": "batang lalaki",
    "translation": "boy"
  },
  {
    "word": "kasintahan",
    "translation": "boyfriend"
  },
  {
    "word": "utak",
    "translation": "brain"
  },
  {
    "word": "sangay",
    "translation": "branch"
  },
  {
    "word": "tatak",
    "translation": "brand"
  },
  {
    "word": "tinapay",
    "translation": "bread"
  },
  {
    "word": "pahinga",
    "translation": "break"
  },
  {
    "word": "almusal",
    "translation": "breakfast"
  },
  {
    "word": "suso",
    "translation": "breast"
  },
  {
    "word": "hininga",
    "translation": "breath"
  },
  {
    "word": "huminga",
    "translation": "breathe"
  },
  {
    "word": "tulay",
    "translation": "bridge"
  },
  {
    "word": "maikli",
    "translation": "brief"
  },
  {
    "word": "sa madaling sabi",
    "translation": "briefly"
  },
  {
    "word": "maliwanag",
    "translation": "bright"
  },
  {
    "word": "napakatalino",
    "translation": "brilliant"
  },
  {
    "word": "magdala",
    "translation": "bring"
  },
  {
    "word": "British",
    "translation": "British"
  },
  {
    "word": "malawak",
    "translation": "broad"
  },
  {
    "word": "sira",
    "translation": "broken"
  },
  {
    "word": "kapatid na lalaki",
    "translation": "brother"
  },
  {
    "word": "kayumanggi",
    "translation": "brown"
  },
  {
    "word": "build",
    "translation": "build"
  },
  {
    "word": "gusali",
    "translation": "building"
  },
  {
    "word": "bala",
    "translation": "bullet"
  },
  {
    "word": "pasan",
    "translation": "burden"
  },
  {
    "word": "sumunog",
    "translation": "burn"
  },
  {
    "word": "ilibing",
    "translation": "bury"
  },
  {
    "word": "bus",
    "translation": "bus"
  },
  {
    "word": "negosyo",
    "translation": "business"
  },
  {
    "word": "abala",
    "translation": "busy"
  },
  {
    "word": "pero",
    "translation": "but"
  },
  {
    "word": "mantikilya",
    "translation": "butter"
  },
  {
    "word": "butones",
    "translation": "button"
  },
  {
    "word": "bili",
    "translation": "buy"
  },
  {
    "word": "bumibili",
    "translation": "buyer"
  },
  {
    "word": "cabin",
    "translation": "cabin"
  },
  {
    "word": "gabinete",
    "translation": "cabinet"
  },
  {
    "word": "kable",
    "translation": "cable"
  },
  {
    "word": "keyk",
    "translation": "cake"
  },
  {
    "word": "kalkulahin",
    "translation": "calculate"
  },
  {
    "word": "tawag",
    "translation": "call"
  },
  {
    "word": "camera",
    "translation": "camera"
  },
  {
    "word": "kampo",
    "translation": "camp"
  },
  {
    "word": "kampanya",
    "translation": "campaign"
  },
  {
    "word": "kampus",
    "translation": "campus"
  },
  {
    "word": "lata",
    "translation": "can"
  },
  {
    "word": "taga-Canada",
    "translation": "Canadian"
  },
  {
    "word": "kanser",
    "translation": "cancer"
  },
  {
    "word": "kandidato",
    "translation": "candidate"
  },
  {
    "word": "kakayahan",
    "translation": "capability"
  },
  {
    "word": "kaya",
    "translation": "capable"
  },
  {
    "word": "kapasidad",
    "translation": "capacity"
  },
  {
    "word": "kabisera",
    "translation": "capital"
  },
  {
    "word": "kapitan",
    "translation": "captain"
  },
  {
    "word": "paghuli",
    "translation": "capture"
  },
  {
    "word": "kotse",
    "translation": "car"
  },
  {
    "word": "karbon",
    "translation": "carbon"
  },
  {
    "word": "kard",
    "translation": "card"
  },
  {
    "word": "alaga",
    "translation": "care"
  },
  {
    "word": "karera",
    "translation": "career"
  },
  {
    "word": "maingat",
    "translation": "careful"
  },
  {
    "word": "maingat",
    "translation": "carefully"
  },
  {
    "word": "tagapagdala",
    "translation": "carrier"
  },
  {
    "word": "buhat",
    "translation": "carry"
  },
  {
    "word": "kaso",
    "translation": "case"
  },
  {
    "word": "pera",
    "translation": "cash"
  },
  {
    "word": "pusa",
    "translation": "cat"
  },
  {
    "word": "kolonyal",
    "translation": "colonial"
  },
  {
    "word": "kulay",
    "translation": "color"
  },
  {
    "word": "haligi",
    "translation": "column"
  },
  {
    "word": "kombinasyon",
    "translation": "combination"
  },
  {
    "word": "pagsamahin",
    "translation": "combine"
  },
  {
    "word": "dumating",
    "translation": "come"
  },
  {
    "word": "komedya",
    "translation": "comedy"
  },
  {
    "word": "ginhawa",
    "translation": "comfort"
  },
  {
    "word": "maginhawa",
    "translation": "comfortable"
  },
  {
    "word": "utos",
    "translation": "command"
  },
  {
    "word": "kumander",
    "translation": "commander"
  },
  {
    "word": "komentaryo",
    "translation": "comment"
  },
  {
    "word": "komersyal",
    "translation": "commercial"
  },
  {
    "word": "komisyon",
    "translation": "commission"
  },
  {
    "word": "mangako",
    "translation": "commit"
  },
  {
    "word": "pangako",
    "translation": "commitment"
  },
  {
    "word": "komite",
    "translation": "committee"
  },
  {
    "word": "karaniwan",
    "translation": "common"
  },
  {
    "word": "makipag-usap",
    "translation": "communicate"
  },
  {
    "word": "pakikipag-usap",
    "translation": "communication"
  },
  {
    "word": "komunidad",
    "translation": "community"
  },
  {
    "word": "kompanya",
    "translation": "company"
  },
  {
    "word": "ihambing",
    "translation": "compare"
  },
  {
    "word": "paghahambing",
    "translation": "comparison"
  },
  {
    "word": "makipagkumpetensya",
    "translation": "compete"
  },
  {
    "word": "paligsahan",
    "translation": "competition"
  },
  {
    "word": "kasali sa paligsahan",
    "translation": "competitor"
  },
  {
    "word": "magreklamo",
    "translation": "complain"
  },
  {
    "word": "reklamo",
    "translation": "complaint"
  },
  {
    "word": "tapos",
    "translation": "complete"
  },
  {
    "word": "ganap",
    "translation": "completely"
  },
  {
    "word": "mahirap unawain",
    "translation": "complex"
  },
  {
    "word": "magulo",
    "translation": "complicated"
  },
  {
    "word": "bahagi",
    "translation": "component"
  },
  {
    "word": "komposisyon",
    "translation": "composition"
  },
  {
    "word": "komprehensibong",
    "translation": "comprehensive"
  },
  {
    "word": "pag-isiping mabuti",
    "translation": "concentrate"
  },
  {
    "word": "konsentrasyon",
    "translation": "concentration"
  },
  {
    "word": "konsepto",
    "translation": "concept"
  },
  {
    "word": "pag-aalala",
    "translation": "concern"
  },
  {
    "word": "nag-aalala",
    "translation": "concerned"
  },
  {
    "word": "konsiyerto",
    "translation": "concert"
  },
  {
    "word": "tapusin",
    "translation": "conclude"
  },
  {
    "word": "konklusyon",
    "translation": "conclusion"
  },
  {
    "word": "kongkreto",
    "translation": "concrete"
  },
  {
    "word": "kalagayan",
    "translation": "condition"
  },
  {
    "word": "pag-uugali",
    "translation": "conduct"
  },
  {
    "word": "pagpupulong",
    "translation": "conference"
  },
  {
    "word": "kumpiyansa",
    "translation": "confidence"
  },
  {
    "word": "nagtitiwala",
    "translation": "confident"
  },
  {
    "word": "kumpirmahin",
    "translation": "confirm"
  },
  {
    "word": "hindi pagkakasundo",
    "translation": "conflict"
  },
  {
    "word": "harapin",
    "translation": "confront"
  },
  {
    "word": "pagkalito",
    "translation": "confusion"
  },
  {
    "word": "kongreso",
    "translation": "Congress"
  },
  {
    "word": "pakongreso",
    "translation": "congressional"
  },
  {
    "word": "pagkonekta",
    "translation": "connect"
  },
  {
    "word": "koneksyon",
    "translation": "connection"
  },
  {
    "word": "malay",
    "translation": "consciousness"
  },
  {
    "word": "pinagkasunduan",
    "translation": "consensus"
  },
  {
    "word": "kinahinatnan",
    "translation": "consequence"
  },
  {
    "word": "konserbatibo",
    "translation": "conservative"
  },
  {
    "word": "isaalang-alang",
    "translation": "consider"
  },
  {
    "word": "pagsasaalang-alang",
    "translation": "consideration"
  },
  {
    "word": "binubuo",
    "translation": "consist"
  },
  {
    "word": "naaalinsunod",
    "translation": "consistent"
  },
  {
    "word": "hindi nagbabago",
    "translation": "constant"
  },
  {
    "word": "patuloy",
    "translation": "constantly"
  },
  {
    "word": "bumubuo",
    "translation": "constitute"
  },
  {
    "word": "konstitusyon",
    "translation": "constitutional"
  },
  {
    "word": "tayuan",
    "translation": "construct"
  },
  {
    "word": "konstruksyon",
    "translation": "construction"
  },
  {
    "word": "konsultant",
    "translation": "consultant"
  },
  {
    "word": "ubusin",
    "translation": "consume"
  },
  {
    "word": "mamimili",
    "translation": "consumer"
  },
  {
    "word": "paggamit",
    "translation": "consumption"
  },
  {
    "word": "naglalaman",
    "translation": "contain"
  },
  {
    "word": "lalagyan",
    "translation": "container"
  },
  {
    "word": "kapanahon",
    "translation": "contemporary"
  },
  {
    "word": "nilalaman",
    "translation": "content"
  },
  {
    "word": "paligsahan",
    "translation": "contest"
  },
  {
    "word": "konteksto",
    "translation": "context"
  },
  {
    "word": "magpatuloy",
    "translation": "continue"
  },
  {
    "word": "patuloy",
    "translation": "continued"
  },
  {
    "word": "kontrata",
    "translation": "contract"
  },
  {
    "word": "kaibahan",
    "translation": "contrast"
  },
  {
    "word": "mag-ambag",
    "translation": "contribute"
  },
  {
    "word": "kontribusyon",
    "translation": "contribution"
  },
  {
    "word": "kontrol",
    "translation": "control"
  },
  {
    "word": "kontrobersyal",
    "translation": "controversial"
  },
  {
    "word": "kapulungan",
    "translation": "convention"
  },
  {
    "word": "pag-uusap",
    "translation": "conversation"
  },
  {
    "word": "palitan",
    "translation": "convert"
  },
  {
    "word": "pananalig",
    "translation": "conviction"
  },
  {
    "word": "kumbinsihin",
    "translation": "convince"
  },
  {
    "word": "lutuin",
    "translation": "cook"
  },
  {
    "word": "galyetas",
    "translation": "cookie"
  },
  {
    "word": "nagluluto",
    "translation": "cooking"
  },
  {
    "word": "kalamigan",
    "translation": "cool"
  },
  {
    "word": "kooperasyon",
    "translation": "cooperation"
  },
  {
    "word": "pulis",
    "translation": "cop"
  },
  {
    "word": "makaya",
    "translation": "cope"
  },
  {
    "word": "kopya",
    "translation": "copy"
  },
  {
    "word": "kaibuturan",
    "translation": "core"
  },
  {
    "word": "mais",
    "translation": "corn"
  },
  {
    "word": "sulok",
    "translation": "corner"
  },
  {
    "word": "korporasyon",
    "translation": "corporation"
  },
  {
    "word": "tama",
    "translation": "correct"
  },
  {
    "word": "kasulatan",
    "translation": "correspondent"
  },
  {
    "word": "gastos",
    "translation": "cost"
  },
  {
    "word": "bulak",
    "translation": "cotton"
  },
  {
    "word": "sopa",
    "translation": "couch"
  },
  {
    "word": "maaari",
    "translation": "could"
  },
  {
    "word": "konseho",
    "translation": "council"
  },
  {
    "word": "tagapayo",
    "translation": "counselor"
  },
  {
    "word": "bilang",
    "translation": "count"
  },
  {
    "word": "bansa",
    "translation": "country"
  },
  {
    "word": "lalawigan",
    "translation": "county"
  },
  {
    "word": "pareha",
    "translation": "couple"
  },
  {
    "word": "tapang",
    "translation": "courage"
  },
  {
    "word": "kurso",
    "translation": "course"
  },
  {
    "word": "korte",
    "translation": "court"
  },
  {
    "word": "pinsan",
    "translation": "cousin"
  },
  {
    "word": "takip",
    "translation": "cover"
  },
  {
    "word": "saklaw",
    "translation": "coverage"
  },
  {
    "word": "baka",
    "translation": "cow"
  },
  {
    "word": "lamat",
    "translation": "crack"
  },
  {
    "word": "katha",
    "translation": "craft"
  },
  {
    "word": "salpukan",
    "translation": "crash"
  },
  {
    "word": "baliw",
    "translation": "crazy"
  },
  {
    "word": "krema",
    "translation": "cream"
  },
  {
    "word": "lumikha",
    "translation": "create"
  },
  {
    "word": "likha",
    "translation": "creation"
  },
  {
    "word": "malikhain",
    "translation": "creative"
  },
  {
    "word": "nilalang",
    "translation": "creature"
  },
  {
    "word": "kredito",
    "translation": "credit"
  },
  {
    "word": "tripulante",
    "translation": "crew"
  },
  {
    "word": "krimen",
    "translation": "crime"
  },
  {
    "word": "kriminal",
    "translation": "criminal"
  },
  {
    "word": "krisis",
    "translation": "crisis"
  },
  {
    "word": "pamantayan",
    "translation": "criteria"
  },
  {
    "word": "kritiko",
    "translation": "critic"
  },
  {
    "word": "mapanuri",
    "translation": "critical"
  },
  {
    "word": "pagpuna",
    "translation": "criticism"
  },
  {
    "word": "pumuna",
    "translation": "criticize"
  },
  {
    "word": "krus",
    "translation": "cross"
  },
  {
    "word": "kulupon",
    "translation": "crowd"
  },
  {
    "word": "krusyal",
    "translation": "crucial"
  },
  {
    "word": "iyak",
    "translation": "cry"
  },
  {
    "word": "kultural",
    "translation": "cultural"
  },
  {
    "word": "kultura",
    "translation": "culture"
  },
  {
    "word": "tasa",
    "translation": "cup"
  },
  {
    "word": "mausisa",
    "translation": "curious"
  },
  {
    "word": "kasalukuyan",
    "translation": "current"
  },
  {
    "word": "sa kasalukuyan",
    "translation": "currently"
  },
  {
    "word": "kurikulum",
    "translation": "curriculum"
  },
  {
    "word": "pasadya",
    "translation": "custom"
  },
  {
    "word": "kostumer",
    "translation": "customer"
  },
  {
    "word": "hiwa",
    "translation": "cut"
  },
  {
    "word": "siklo",
    "translation": "cycle"
  },
  {
    "word": "tatay",
    "translation": "dad"
  },
  {
    "word": "araw-araw",
    "translation": "daily"
  },
  {
    "word": "pinsala",
    "translation": "damage"
  },
  {
    "word": "sayaw",
    "translation": "dance"
  },
  {
    "word": "panganib",
    "translation": "danger"
  },
  {
    "word": "mapanganib",
    "translation": "dangerous"
  },
  {
    "word": "hamon",
    "translation": "dare"
  },
  {
    "word": "madilim",
    "translation": "dark"
  },
  {
    "word": "kadiliman",
    "translation": "darkness"
  },
  {
    "word": "datos",
    "translation": "data"
  },
  {
    "word": "petsa",
    "translation": "date"
  },
  {
    "word": "araw",
    "translation": "day"
  },
  {
    "word": "patay",
    "translation": "dead"
  },
  {
    "word": "pakikitungo",
    "translation": "deal"
  },
  {
    "word": "minamahal",
    "translation": "dear"
  },
  {
    "word": "kamatayan",
    "translation": "death"
  },
  {
    "word": "debate",
    "translation": "debate"
  },
  {
    "word": "utang",
    "translation": "debt"
  },
  {
    "word": "dekada",
    "translation": "decade"
  },
  {
    "word": "magpasya",
    "translation": "decide"
  },
  {
    "word": "desisyon",
    "translation": "decision"
  },
  {
    "word": "ideklara",
    "translation": "declare"
  },
  {
    "word": "tanggihan",
    "translation": "decline"
  },
  {
    "word": "pagbaba",
    "translation": "decrease"
  },
  {
    "word": "lalim",
    "translation": "deep"
  },
  {
    "word": "malalim",
    "translation": "deeply"
  },
  {
    "word": "usa",
    "translation": "deer"
  },
  {
    "word": "pagkatalo",
    "translation": "defeat"
  },
  {
    "word": "magtanggol",
    "translation": "defend"
  },
  {
    "word": "pagtatanggol",
    "translation": "defense"
  },
  {
    "word": "kakulangan",
    "translation": "deficit"
  }
]
